COPYING
COPYING.lesser
MANIFEST.in
NOTICE
README.md
requirements.txt
setup.py
agram/__init__.py
agram/client.py
agram/dispatcher.py
agram/emoji.py
agram/file_id.py
agram/filters.py
agram/mime_types.py
agram/py.typed
agram/sync.py
agram/utils.py
agram.egg-info/PKG-INFO
agram.egg-info/SOURCES.txt
agram.egg-info/dependency_links.txt
agram.egg-info/not-zip-safe
agram.egg-info/requires.txt
agram.egg-info/top_level.txt
agram/connection/__init__.py
agram/connection/connection.py
agram/connection/transport/__init__.py
agram/connection/transport/tcp/__init__.py
agram/connection/transport/tcp/tcp.py
agram/connection/transport/tcp/tcp_abridged.py
agram/connection/transport/tcp/tcp_abridged_o.py
agram/connection/transport/tcp/tcp_full.py
agram/connection/transport/tcp/tcp_intermediate.py
agram/connection/transport/tcp/tcp_intermediate_o.py
agram/crypto/__init__.py
agram/crypto/aes.py
agram/crypto/mtproto.py
agram/crypto/prime.py
agram/crypto/rsa.py
agram/enums/__init__.py
agram/enums/auto_name.py
agram/enums/chat_action.py
agram/enums/chat_event_action.py
agram/enums/chat_member_status.py
agram/enums/chat_members_filter.py
agram/enums/chat_type.py
agram/enums/message_entity_type.py
agram/enums/message_media_type.py
agram/enums/message_service_type.py
agram/enums/messages_filter.py
agram/enums/next_code_type.py
agram/enums/parse_mode.py
agram/enums/poll_type.py
agram/enums/sent_code_type.py
agram/enums/user_status.py
agram/errors/__init__.py
agram/errors/rpc_error.py
agram/handlers/__init__.py
agram/handlers/callback_query_handler.py
agram/handlers/chat_join_request_handler.py
agram/handlers/chat_member_updated_handler.py
agram/handlers/chosen_inline_result_handler.py
agram/handlers/deleted_messages_handler.py
agram/handlers/disconnect_handler.py
agram/handlers/edited_message_handler.py
agram/handlers/handler.py
agram/handlers/inline_query_handler.py
agram/handlers/message_handler.py
agram/handlers/poll_handler.py
agram/handlers/raw_update_handler.py
agram/handlers/user_status_handler.py
agram/methods/__init__.py
agram/methods/advanced/__init__.py
agram/methods/advanced/invoke.py
agram/methods/advanced/resolve_peer.py
